kinetica_provider/__init__.py
kinetica_provider/get_provider_info.py
kinetica_provider/hooks/__init__.py
kinetica_provider/hooks/sql.py
kinetica_provider/operator/__init__.py
kinetica_provider/operator/spark.py
kinetica_provider/operator/sql.py
airflow_provider_kinetica-1.0.3.dist-info/LICENSE
airflow_provider_kinetica-1.0.3.dist-info/METADATA
airflow_provider_kinetica-1.0.3.dist-info/WHEEL
airflow_provider_kinetica-1.0.3.dist-info/entry_points.txt
airflow_provider_kinetica-1.0.3.dist-info/top_level.txt
airflow_provider_kinetica-1.0.3.dist-info/RECORD
