Metadata-Version: 2.1
Name: airflow-provider-kinetica
Version: 1.0.3
Summary: Kinetica Airflow provider package
Author-email: Chad Juliano <cjuliano@kinetica.com>
License: MIT License
Project-URL: Homepage, https://kinetica.com
Project-URL: Documentation, https://github.com/kineticadb/kinetica-airflow
Project-URL: Repository, https://github.com/kineticadb/kinetica-airflow
Classifier: Programming Language :: Python :: 3
Classifier: Framework :: Apache Airflow
Classifier: Framework :: Apache Airflow :: Provider
Classifier: Development Status :: 5 - Production/Stable
Classifier: Intended Audience :: System Administrators
Classifier: License :: OSI Approved :: MIT License
Requires-Python: ~=3.8
License-File: LICENSE
Requires-Dist: apache-airflow >=2.3
Requires-Dist: gpudb
Requires-Dist: apache-airflow-providers-apache-spark
